LICENSE
README.md
setup.py
aiogram_dialog/__init__.py
aiogram_dialog/dialog.py
aiogram_dialog/utils.py
aiogram_dialog/window.py
aiogram_dialog/api/__init__.py
aiogram_dialog/api/exceptions.py
aiogram_dialog/api/entities/__init__.py
aiogram_dialog/api/entities/context.py
aiogram_dialog/api/entities/events.py
aiogram_dialog/api/entities/launch_mode.py
aiogram_dialog/api/entities/media.py
aiogram_dialog/api/entities/modes.py
aiogram_dialog/api/entities/new_message.py
aiogram_dialog/api/entities/stack.py
aiogram_dialog/api/entities/update_event.py
aiogram_dialog/api/internal/__init__.py
aiogram_dialog/api/internal/fake_data.py
aiogram_dialog/api/internal/manager.py
aiogram_dialog/api/internal/middleware.py
aiogram_dialog/api/internal/widgets.py
aiogram_dialog/api/internal/window.py
aiogram_dialog/api/protocols/__init__.py
aiogram_dialog/api/protocols/dialog.py
aiogram_dialog/api/protocols/manager.py
aiogram_dialog/api/protocols/media.py
aiogram_dialog/api/protocols/message_manager.py
aiogram_dialog/api/protocols/registry.py
aiogram_dialog/context/__init__.py
aiogram_dialog/context/intent_filter.py
aiogram_dialog/context/intent_middleware.py
aiogram_dialog/context/media_storage.py
aiogram_dialog/context/storage.py
aiogram_dialog/manager/__init__.py
aiogram_dialog/manager/bg_manager.py
aiogram_dialog/manager/manager.py
aiogram_dialog/manager/manager_middleware.py
aiogram_dialog/manager/message_manager.py
aiogram_dialog/manager/registry.py
aiogram_dialog/manager/sub_manager.py
aiogram_dialog/manager/update_handler.py
aiogram_dialog/tools/__init__.py
aiogram_dialog/tools/calculator.png
aiogram_dialog/tools/preview.py
aiogram_dialog/tools/transitions.py
aiogram_dialog/tools/templates/__init__.py
aiogram_dialog/tools/templates/message.html
aiogram_dialog/widgets/__init__.py
aiogram_dialog/widgets/utils.py
aiogram_dialog/widgets/widget_event.py
aiogram_dialog/widgets/common/__init__.py
aiogram_dialog/widgets/common/action.py
aiogram_dialog/widgets/common/base.py
aiogram_dialog_data_ttl_patched.egg-info/PKG-INFO
aiogram_dialog_data_ttl_patched.egg-info/SOURCES.txt
aiogram_dialog_data_ttl_patched.egg-info/dependency_links.txt
aiogram_dialog_data_ttl_patched.egg-info/requires.txt
aiogram_dialog_data_ttl_patched.egg-info/top_level.txt