Metadata-Version: 2.1
Name: aiogram-dialog-data-ttl-patched
Version: 2.0.0b15
Summary: Mini-framework for dialogs on top of aiogram
Home-page: https://github.com/tishka17/aiogram_dialog
Author: A. Tikhonov
Author-email: 17@itishka.org
License: Apache2
Platform: UNKNOWN
Classifier: Operating System :: OS Independent
Classifier: Intended Audience :: Developers
Classifier: License :: OSI Approved :: Apache Software License
Classifier: Programming Language :: Python :: 3
Requires-Python: >=3.8
Provides-Extra: tools
License-File: LICENSE
